newrelic_mcp/__init__.py
newrelic_mcp/__main__.py
newrelic_mcp/credentials.py
newrelic_mcp/log_parsing.py
newrelic_mcp/server.py
newrelic_mcp_server-1.3.1.dist-info/licenses/LICENSE
newrelic_mcp_server-1.3.1.dist-info/METADATA
newrelic_mcp_server-1.3.1.dist-info/WHEEL
newrelic_mcp_server-1.3.1.dist-info/entry_points.txt
newrelic_mcp_server-1.3.1.dist-info/top_level.txt
newrelic_mcp_server-1.3.1.dist-info/RECORD
