Metadata-Version: 2.4
Name: newrelic-mcp-server
Version: 1.3.1
Summary: New Relic MCP Server - Model Context Protocol server for New Relic APIs
Author-email: Caleb Piekstra <calebpiekstra@gmail.com>
License: MIT
Project-URL: Homepage, https://github.com/piekstra/newrelic-mcp-server
Project-URL: Repository, https://github.com/piekstra/newrelic-mcp-server
Project-URL: Issues, https://github.com/piekstra/newrelic-mcp-server/issues
Project-URL: Documentation, https://github.com/piekstra/newrelic-mcp-server#readme
Keywords: newrelic,mcp,monitoring,observability,claude,ai
Classifier: Development Status :: 5 - Production/Stable
Classifier: Intended Audience :: Developers
Classifier: License :: OSI Approved :: MIT License
Classifier: Operating System :: OS Independent
Classifier: Programming Language :: Python :: 3
Classifier: Programming Language :: Python :: 3.10
Classifier: Programming Language :: Python :: 3.11
Classifier: Programming Language :: Python :: 3.12
Classifier: Topic :: Software Development :: Libraries :: Python Modules
Classifier: Topic :: System :: Monitoring
Classifier: Topic :: Internet :: WWW/HTTP :: Dynamic Content
Requires-Python: >=3.10
License-File: LICENSE
Requires-Dist: fastmcp>=0.1.0
Requires-Dist: httpx>=0.24.0
Requires-Dist: keyring>=24.0.0
Provides-Extra: dev
Requires-Dist: pytest>=7.0.0; extra == "dev"
Requires-Dist: pytest-asyncio>=0.21.0; extra == "dev"
Requires-Dist: black>=23.0.0; extra == "dev"
Requires-Dist: flake8>=5.0.0; extra == "dev"
Requires-Dist: isort>=5.12.0; extra == "dev"
Requires-Dist: mypy>=1.0.0; extra == "dev"
Requires-Dist: pre-commit>=3.0.0; extra == "dev"
Dynamic: license-file
